tidyfasta/__init__.py
tidyfasta/__main__.py
tidyfasta/common/__init__.py
tidyfasta/common/process.py
tidyfasta-1.0.5.dist-info/METADATA
tidyfasta-1.0.5.dist-info/WHEEL
tidyfasta-1.0.5.dist-info/entry_points.txt
tidyfasta-1.0.5.dist-info/top_level.txt
tidyfasta-1.0.5.dist-info/RECORD
