Metadata-Version: 2.1
Name: tidyfasta
Version: 1.0.5
Summary: Sanitise protein FASTA files / data
Home-page: https://github.com/maxhebditch/tidyfasta
Author: Max Hebditch
Author-email: max@maxhebditch.co.uk
License: MIT
Platform: UNKNOWN
